gitllama/__init__.py
gitllama/cli.py
gitllama/config.py
gitllama/ai/__init__.py
gitllama/ai/client.py
gitllama/ai/congress.py
gitllama/ai/context_compressor.py
gitllama/ai/parser.py
gitllama/ai/query.py
gitllama/core/__init__.py
gitllama/core/coordinator.py
gitllama/core/git_operations.py
gitllama/todo/__init__.py
gitllama/todo/analyzer.py
gitllama/todo/executor.py
gitllama/todo/planner.py
gitllama/utils/__init__.py
gitllama/utils/config.py
gitllama/utils/context_tracker.py
gitllama/utils/metrics.py
gitllama/utils/reports.py
gitllama-0.7.3.dist-info/METADATA
gitllama-0.7.3.dist-info/WHEEL
gitllama-0.7.3.dist-info/entry_points.txt
gitllama-0.7.3.dist-info/licenses/LICENSE
gitllama-0.7.3.dist-info/RECORD
